<?xml version="1.0"?>
<!DOCTYPE hibernate-mapping PUBLIC "-//Hibernate/Hibernate Mapping DTD 3.0//EN"
"http://www.hibernate.org/dtd/hibernate-mapping-3.0.dtd">
<!-- Generated 1 dic 2022 17:53:52 by Hibernate Tools 4.3.6.Final -->
<hibernate-mapping>
    <class name="modelo.Departamentos" table="departamentos" catalog="empresa" optimistic-lock="version">
        <id name="dptoNo" type="int">
            <column name="dpto_no" />
            <generator class="assigned" />
        </id>
        <property name="dnombre" type="string">
            <column name="dnombre" length="50" />
        </property>
        <property name="loc" type="string">
            <column name="loc" length="50" />
        </property>
        <set name="empleadoses" table="empleados" inverse="true" lazy="true" fetch="select">
            <key>
                <column name="dpto_no" not-null="true" />
            </key>
            <one-to-many class="modelo.Empleados" />
        </set>
    </class>
</hibernate-mapping>
